dmake/__init__.py
dmake/aws.py
dmake/azure.py
dmake/base_commands.py
dmake/cmd.py
dmake/command_registry.py
dmake/common.py
dmake/config.py
dmake/deploy.py
dmake/doc.py
dmake/release.py
dmake/stack.py
dmake/status.py
dmake/templates/docker-compose.yml
dmake/templates/docker-env.yml
dmake/templates/settings-common.env.tpl
dmake/templates/settings-dev.env.tpl
dmake-0.0.1.dev48.dist-info/AUTHORS
dmake-0.0.1.dev48.dist-info/LICENSE
dmake-0.0.1.dev48.dist-info/METADATA
dmake-0.0.1.dev48.dist-info/WHEEL
dmake-0.0.1.dev48.dist-info/entry_points.txt
dmake-0.0.1.dev48.dist-info/pbr.json
dmake-0.0.1.dev48.dist-info/top_level.txt
dmake-0.0.1.dev48.dist-info/RECORD
