Metadata-Version: 2.1
Name: dmake
Version: 0.0.1.dev48
Summary: A Docker+Swarm-based CI toolset frontend
Home-page: https://dmake.org
Author: NumeriCube
Author-email: support@numericube.com
License: GPL-2
Project-URL: Bug Tracker, https://github.com/numericube/dmake
Project-URL: Documentation, https://github.com/numericube/dmake
Project-URL: Source Code, https://github.com/numericube/dmake
Keywords: docker,CI
Platform: UNKNOWN
Classifier: Development Status :: 4 - Beta
Classifier: Environment :: Console
Classifier: Intended Audience :: Developers
Classifier: Intended Audience :: Information Technology
Classifier: Operating System :: OS Independent
Classifier: Programming Language :: Python
Requires-Python: >=3.4
License-File: LICENSE
License-File: AUTHORS
Requires-Dist: ruamel.yaml
